locoprop/__init__.py
locoprop/layer.py
locoprop/trainer.py
locoprop-0.1.0.dist-info/LICENSE
locoprop-0.1.0.dist-info/METADATA
locoprop-0.1.0.dist-info/WHEEL
locoprop-0.1.0.dist-info/top_level.txt
locoprop-0.1.0.dist-info/RECORD
