Metadata-Version: 2.1
Name: locoprop
Version: 0.1.0
Summary: LocoProp implementation in PyTorch.
Author: Dimitri von Rütte
License: MIT
Project-URL: github, https://github.com/dvruette/locoprop-torch
License-File: LICENSE
Requires-Dist: torch
